_raspy2mqtt_version.py
raspy2mqtt/__init__.py
raspy2mqtt/circular_buffer.py
raspy2mqtt/config.py
raspy2mqtt/constants.py
raspy2mqtt/gpio_inputs_handler.py
raspy2mqtt/gpio_outputs_handler.py
raspy2mqtt/homeassistant_status_tracker.py
raspy2mqtt/main.py
raspy2mqtt/optoisolated_inputs_handler.py
raspy2mqtt/stats.py
rpi2home_assistant-2.3.2.dist-info/METADATA
rpi2home_assistant-2.3.2.dist-info/WHEEL
rpi2home_assistant-2.3.2.dist-info/entry_points.txt
rpi2home_assistant-2.3.2.dist-info/licenses/LICENSE
rpi2home_assistant-2.3.2.dist-info/RECORD
