Metadata-Version: 2.4
Name: rpi2home-assistant
Version: 2.3.2
Summary: Raspberry PI to Home Assistant bridge through MQTT for wired sensors/actuators
Project-URL: Homepage, https://github.com/f18m/rpi2home-assistant
Project-URL: Bug Tracker, https://github.com/f18m/rpi2home-assistant/issues
Author-email: Francesco Montorsi <francesco.montorsi.nospam@gmail.com>
License-File: LICENSE
Classifier: License :: OSI Approved :: MIT License
Classifier: Operating System :: OS Independent
Classifier: Programming Language :: Python :: 3
Requires-Dist: aiomqtt==2.5.0
Requires-Dist: gpiozero==2.0.1
Requires-Dist: pigpio==1.78
Requires-Dist: pyyaml==6.0.3
Requires-Dist: schema==0.7.8
Requires-Dist: sm16inpind==1.1.5
